{
  "33": {
    "LHODGLFENEN": 33,
    "HBDNEEBMLPG": true
  },
  "18001": {
    "LHODGLFENEN": 18001,
    "HBDNEEBMLPG": true
  },
  "18002": {
    "LHODGLFENEN": 18002,
    "HBDNEEBMLPG": true
  },
  "18003": {
    "LHODGLFENEN": 18003,
    "HBDNEEBMLPG": true
  },
  "18004": {
    "LHODGLFENEN": 18004,
    "HBDNEEBMLPG": true
  },
  "140004": {
    "LHODGLFENEN": 140004
  },
  "140037": {
    "LHODGLFENEN": 140037
  },
  "140074": {
    "LHODGLFENEN": 140074
  },
  "140000": {
    "LHODGLFENEN": 140000,
    "HBDNEEBMLPG": true
  },
  "140247": {
    "LHODGLFENEN": 140247
  },
  "140248": {
    "LHODGLFENEN": 140248
  },
  "140250": {
    "LHODGLFENEN": 140250
  },
  "140251": {
    "LHODGLFENEN": 140251
  },
  "140252": {
    "LHODGLFENEN": 140252
  },
  "140253": {
    "LHODGLFENEN": 140253
  },
  "140254": {
    "LHODGLFENEN": 140254
  },
  "140255": {
    "LHODGLFENEN": 140255
  },
  "140256": {
    "LHODGLFENEN": 140256
  },
  "140257": {
    "LHODGLFENEN": 140257
  },
  "140320": {
    "LHODGLFENEN": 140320
  },
  "140324": {
    "LHODGLFENEN": 140324
  },
  "140325": {
    "LHODGLFENEN": 140325
  },
  "250200": {
    "LHODGLFENEN": 250200,
    "HBDNEEBMLPG": true
  },
  "250201": {
    "LHODGLFENEN": 250201,
    "HBDNEEBMLPG": true
  },
  "250202": {
    "LHODGLFENEN": 250202,
    "HBDNEEBMLPG": true
  },
  "250203": {
    "LHODGLFENEN": 250203,
    "HBDNEEBMLPG": true
  },
  "250204": {
    "LHODGLFENEN": 250204,
    "HBDNEEBMLPG": true
  },
  "250205": {
    "LHODGLFENEN": 250205,
    "HBDNEEBMLPG": true
  },
  "250206": {
    "LHODGLFENEN": 250206,
    "HBDNEEBMLPG": true
  },
  "250207": {
    "LHODGLFENEN": 250207,
    "HBDNEEBMLPG": true
  },
  "250208": {
    "LHODGLFENEN": 250208,
    "HBDNEEBMLPG": true
  },
  "250209": {
    "LHODGLFENEN": 250209,
    "HBDNEEBMLPG": true
  },
  "250210": {
    "LHODGLFENEN": 250210,
    "HBDNEEBMLPG": true
  },
  "250211": {
    "LHODGLFENEN": 250211,
    "HBDNEEBMLPG": true
  },
  "250212": {
    "LHODGLFENEN": 250212,
    "HBDNEEBMLPG": true
  },
  "250213": {
    "LHODGLFENEN": 250213,
    "HBDNEEBMLPG": true
  },
  "250214": {
    "LHODGLFENEN": 250214,
    "HBDNEEBMLPG": true
  },
  "250215": {
    "LHODGLFENEN": 250215,
    "HBDNEEBMLPG": true
  },
  "250216": {
    "LHODGLFENEN": 250216,
    "HBDNEEBMLPG": true
  },
  "250217": {
    "LHODGLFENEN": 250217,
    "HBDNEEBMLPG": true
  },
  "250218": {
    "LHODGLFENEN": 250218,
    "HBDNEEBMLPG": true
  },
  "250219": {
    "LHODGLFENEN": 250219,
    "HBDNEEBMLPG": true
  },
  "250220": {
    "LHODGLFENEN": 250220,
    "HBDNEEBMLPG": true
  },
  "250221": {
    "LHODGLFENEN": 250221,
    "HBDNEEBMLPG": true
  },
  "250222": {
    "LHODGLFENEN": 250222,
    "HBDNEEBMLPG": true
  },
  "250223": {
    "LHODGLFENEN": 250223,
    "HBDNEEBMLPG": true
  },
  "250224": {
    "LHODGLFENEN": 250224,
    "HBDNEEBMLPG": true
  },
  "250225": {
    "LHODGLFENEN": 250225,
    "HBDNEEBMLPG": true
  },
  "250226": {
    "LHODGLFENEN": 250226,
    "HBDNEEBMLPG": true
  },
  "250227": {
    "LHODGLFENEN": 250227,
    "HBDNEEBMLPG": true
  },
  "250228": {
    "LHODGLFENEN": 250228,
    "HBDNEEBMLPG": true
  },
  "250229": {
    "LHODGLFENEN": 250229,
    "HBDNEEBMLPG": true
  },
  "250230": {
    "LHODGLFENEN": 250230,
    "HBDNEEBMLPG": true
  },
  "250231": {
    "LHODGLFENEN": 250231,
    "HBDNEEBMLPG": true
  },
  "250232": {
    "LHODGLFENEN": 250232,
    "HBDNEEBMLPG": true
  },
  "250233": {
    "LHODGLFENEN": 250233,
    "HBDNEEBMLPG": true
  },
  "250320": {
    "LHODGLFENEN": 250320,
    "HBDNEEBMLPG": true
  },
  "250401": {
    "LHODGLFENEN": 250401,
    "HBDNEEBMLPG": true
  },
  "250402": {
    "LHODGLFENEN": 250402,
    "HBDNEEBMLPG": true
  },
  "250403": {
    "LHODGLFENEN": 250403,
    "HBDNEEBMLPG": true
  },
  "250404": {
    "LHODGLFENEN": 250404,
    "HBDNEEBMLPG": true
  },
  "270001": {
    "LHODGLFENEN": 270001,
    "HBDNEEBMLPG": true
  },
  "140400": {
    "LHODGLFENEN": 140400,
    "HBDNEEBMLPG": true
  },
  "140401": {
    "LHODGLFENEN": 140401,
    "HBDNEEBMLPG": true
  }
}